README.rst
setup.py
src/aiohttp_autoreload.py
src/aiohttp_autoreload.egg-info/PKG-INFO
src/aiohttp_autoreload.egg-info/SOURCES.txt
src/aiohttp_autoreload.egg-info/dependency_links.txt
src/aiohttp_autoreload.egg-info/not-zip-safe
src/aiohttp_autoreload.egg-info/top_level.txt