Metadata-Version: 1.1
Name: aiohttp-autoreload
Version: 0.0.1
Summary: Makes aiohttp server autoreload on source code change
Home-page: https://github.com/anti1869/aiohttp_autoreload
Author: Dmitry Litvinenko
Author-email: anti1869@gmail.com
License: Apache 2
Platform: UNKNOWN
Classifier: License :: OSI Approved :: Apache Software License
Classifier: Intended Audience :: Developers
Classifier: Programming Language :: Python
Classifier: Programming Language :: Python :: 3
Classifier: Programming Language :: Python :: 3.4
Classifier: Programming Language :: Python :: 3.5
Classifier: Topic :: Internet :: WWW/HTTP
